cloudshell/__init__.py
cloudshell/shell/__init__.py
cloudshell/shell/flows/__init__.py
cloudshell/shell/flows/interfaces.py
cloudshell/shell/flows/autoload/__init__.py
cloudshell/shell/flows/autoload/autoload_utils.py
cloudshell/shell/flows/autoload/basic_flow.py
cloudshell/shell/flows/command/__init__.py
cloudshell/shell/flows/command/basic_flow.py
cloudshell/shell/flows/configuration/__init__.py
cloudshell/shell/flows/configuration/basic_flow.py
cloudshell/shell/flows/firmware/__init__.py
cloudshell/shell/flows/firmware/basic_flow.py
cloudshell/shell/flows/state/__init__.py
cloudshell/shell/flows/state/basic_flow.py
cloudshell/shell/flows/utils/__init__.py
cloudshell/shell/flows/utils/errors.py
cloudshell/shell/flows/utils/protocols.py
cloudshell/shell/flows/utils/resource_conf.py
cloudshell/shell/flows/utils/str_helpers.py
cloudshell/shell/flows/utils/url.py
tests/__init__.py
tests/conftest.py
tests/cloudshell/__init__.py
tests/cloudshell/shell/__init__.py
tests/cloudshell/shell/flows/__init__.py
tests/cloudshell/shell/flows/test_interfaces.py
tests/cloudshell/shell/flows/autoload/__init__.py
tests/cloudshell/shell/flows/autoload/test_autoload_utils.py
tests/cloudshell/shell/flows/autoload/test_basic_flow.py
tests/cloudshell/shell/flows/command/__init__.py
tests/cloudshell/shell/flows/command/test_basic_flow.py
tests/cloudshell/shell/flows/configuration/__init__.py
tests/cloudshell/shell/flows/configuration/test_configuration_flow.py
tests/cloudshell/shell/flows/firmware/__init__.py
tests/cloudshell/shell/flows/firmware/test_firmware_flow.py
tests/cloudshell/shell/flows/state/__init__.py
tests/cloudshell/shell/flows/state/test_basic_flow.py
tests/cloudshell/shell/flows/utils/__init__.py
tests/cloudshell/shell/flows/utils/test_str_helpers.py
tests/cloudshell/shell/flows/utils/test_url.py
cloudshell_shell_flows-3.0.0.dist-info/LICENSE.htm
cloudshell_shell_flows-3.0.0.dist-info/METADATA
cloudshell_shell_flows-3.0.0.dist-info/WHEEL
cloudshell_shell_flows-3.0.0.dist-info/top_level.txt
cloudshell_shell_flows-3.0.0.dist-info/RECORD
