Metadata-Version: 2.1
Name: cloudshell-shell-flows
Version: 3.0.0
Summary: QualiSystems Shells Flows Package
Home-page: http://www.qualisystems.com/
Author: Quali
Author-email: info@quali.com
Requires-Python: ~=3.7
License-File: LICENSE.htm
Requires-Dist: cloudshell-shell-core (~=6.0)
Requires-Dist: cloudshell-logging (~=2.0)
Requires-Dist: cloudshell-shell-standards (~=2.0)
Requires-Dist: typing-extensions
Requires-Dist: attrs (>=21)
